MultiplierTestSpecterPackage/__init__.py
MultiplierTestSpecterPackage/multiplication.py
MultiplierTestSpecterPackage-1.0.dist-info/METADATA
MultiplierTestSpecterPackage-1.0.dist-info/WHEEL
MultiplierTestSpecterPackage-1.0.dist-info/top_level.txt
MultiplierTestSpecterPackage-1.0.dist-info/RECORD
