Metadata-Version: 2.1
Name: MultiplierTestSpecterPackage
Version: 1.0
Summary: multiply a number by the given multiplier
Author: Specter
Author-email: <sigurd.thornes@gmail.com>
Keywords: python,multiply
Classifier: Development Status :: 1 - Planning
Classifier: Intended Audience :: Developers
Classifier: Programming Language :: Python :: 3
Classifier: Operating System :: Unix
Classifier: Operating System :: MacOS :: MacOS X
Classifier: Operating System :: Microsoft :: Windows
